{
    "lX": 1,
    "lY": 1,
    "sites": [
        {
            "siteId": "A0_(0, 0)",
            "numEntries": 8,
            "entries": [
                "0 0 0 -0.5896848107968506",
                "0 0 1 0.0801955240029135",
                "0 1 0 0.3541606479888803",
                "0 1 1 0.44470721979636013",
                "1 0 0 -0.9467734666290226",
                "1 0 1 0.2554620294544562",
                "1 1 0 -0.5318795542735248",
                "1 1 1 1.0"
            ]
        },
        {
            "siteId": "A1_(0, 0)",
            "numEntries": 8,
            "entries": [
                "0 0 0 0.018765020248557713",
                "0 0 1 1.0",
                "0 1 0 0.00931178192237842",
                "0 1 1 -0.8570607254912436",
                "1 0 0 -0.5025976045264342",
                "1 0 1 0.6611897195917464",
                "1 1 0 0.48644452976726593",
                "1 1 1 -0.22125664682180152"
            ]
        },
        {
            "siteId": "A2_(0, 0)",
            "numEntries": 8,
            "entries": [
                "0 0 0 -0.4917712856237604",
                "0 0 1 -0.68913080493842",
                "0 1 0 -0.18739670715774417",
                "0 1 1 0.580797520412998",
                "1 0 0 0.6407338195803138",
                "1 0 1 1.0",
                "1 1 0 0.6147488470826151",
                "1 1 1 0.30580130085716123"
            ]
        },
        {
            "siteId": "A3_(0, 0)",
            "numEntries": 8,
            "entries": [
                "0 0 0 -0.8834688387748727",
                "0 0 1 0.8518141265103292",
                "0 1 0 0.07987494887743816",
                "0 1 1 1.0",
                "1 0 0 0.5633720291016032",
                "1 0 1 -0.5082194350051833",
                "1 1 0 -0.11710515253292328",
                "1 1 1 0.7644713918897942"
            ]
        },
        {
            "siteId": "A4_(0, 0)",
            "numEntries": 8,
            "entries": [
                "0 0 0 0.618608803403865",
                "0 0 1 0.20730607396975298",
                "0 1 0 0.9341807089518925",
                "0 1 1 0.2719307295993452",
                "1 0 0 -0.16677630049685846",
                "1 0 1 0.6527792834706999",
                "1 1 0 -0.24454983373217987",
                "1 1 1 1.0"
            ]
        }
    ],
    "siteIds": [
        "A0_(0, 0)",
        "A1_(0, 0)",
        "A2_(0, 0)",
        "A3_(0, 0)",
        "A4_(0, 0)"
    ],
    "map": [
        {
            "siteId": "A0_(0, 0)",
            "x": 0,
            "y": 0
        },
        {
            "siteId": "A1_(0, 0)",
            "x": 0,
            "y": 0
        },
        {
            "siteId": "A2_(0, 0)",
            "x": 0,
            "y": 0
        },
        {
            "siteId": "A3_(0, 0)",
            "x": 0,
            "y": 0
        },
        {
            "siteId": "A4_(0, 0)",
            "x": 0,
            "y": 0
        }
    ]
}